lektor_minify/__init__.py
lektor_minify-1.2.dist-info/DESCRIPTION.rst
lektor_minify-1.2.dist-info/METADATA
lektor_minify-1.2.dist-info/RECORD
lektor_minify-1.2.dist-info/WHEEL
lektor_minify-1.2.dist-info/entry_points.txt
lektor_minify-1.2.dist-info/metadata.json
lektor_minify-1.2.dist-info/top_level.txt
