Metadata-Version: 2.0
Name: lektor-minify
Version: 1.2
Summary: Minify build artifacts during the Lektor build process
Home-page: UNKNOWN
Author: Pietro Albini
Author-email: pietro@pietroalbini.org
License: MIT
Platform: UNKNOWN
Classifier: Development Status :: 5 - Production/Stable
Classifier: Environment :: Plugins
Classifier: Intended Audience :: Developers
Classifier: License :: OSI Approved :: MIT License
Classifier: Programming Language :: Python :: 2
Classifier: Programming Language :: Python :: 3
Requires-Dist: django-htmlmin
Requires-Dist: rcssmin
Requires-Dist: rjsmin
